potencent/__init__.py
potencent/api/__init__.py
potencent/api/ocr.py
potencent/core/OCR.py
potencent/core/__init__.py
potencent/lib/CONST.py
potencent/lib/CommonUtils.py
potencent/lib/Config.py
potencent/lib/__init__.py
tests/__init__.py
tests/test_tencent.py
potencent-0.0.4.dist-info/LICENSE
potencent-0.0.4.dist-info/METADATA
potencent-0.0.4.dist-info/WHEEL
potencent-0.0.4.dist-info/top_level.txt
potencent-0.0.4.dist-info/RECORD
