Metadata-Version: 2.1
Name: potencent
Version: 0.0.4
Summary: pip install potencent
Home-page: http://python-office.com/
Author: CoderWanFeng
Author-email: 1957875073@qq.com
License: MIT
Project-URL: Bug Tracker, https://github.com/CoderWanFeng/potencent/issues
Project-URL: Documentation, https://github.com/CoderWanFeng/potencent/blob/main/README.md
Project-URL: Source Code, https://github.com/CoderWanFeng/potencent
Platform: any
Requires-Python: >=3.7
License-File: LICENSE
Requires-Dist: toml
Requires-Dist: tencentcloud-sdk-python
